garth/__init__.py
garth/auth_tokens.py
garth/cli.py
garth/exc.py
garth/http.py
garth/py.typed
garth/sso.py
garth/telemetry.py
garth/utils.py
garth/version.py
garth/data/__init__.py
garth/data/_base.py
garth/data/activity.py
garth/data/daily_sleep_data.py
garth/data/daily_summary.py
garth/data/fitness_stats.py
garth/data/garmin_scores.py
garth/data/heart_rate.py
garth/data/hrv.py
garth/data/morning_training_readiness.py
garth/data/sleep.py
garth/data/training_readiness.py
garth/data/weight.py
garth/data/body_battery/__init__.py
garth/data/body_battery/daily_stress.py
garth/data/body_battery/events.py
garth/data/body_battery/readings.py
garth/stats/__init__.py
garth/stats/_base.py
garth/stats/hrv.py
garth/stats/hydration.py
garth/stats/intensity_minutes.py
garth/stats/sleep.py
garth/stats/steps.py
garth/stats/stress.py
garth/stats/training_status/__init__.py
garth/stats/training_status/daily.py
garth/stats/training_status/monthly.py
garth/stats/training_status/weekly.py
garth/users/__init__.py
garth/users/profile.py
garth/users/settings.py
garth-0.6.2.dist-info/METADATA
garth-0.6.2.dist-info/WHEEL
garth-0.6.2.dist-info/entry_points.txt
garth-0.6.2.dist-info/licenses/LICENSE
garth-0.6.2.dist-info/RECORD
