Metadata-Version: 2.4
Name: garth
Version: 0.6.2
Summary: Garmin SSO auth + Connect client
Project-URL: Homepage, https://github.com/matin/garth
Project-URL: Documentation, https://garth.readthedocs.io
Project-URL: Repository, https://github.com/matin/garth
Project-URL: Issues, https://github.com/matin/garth/issues
Project-URL: Changelog, https://github.com/matin/garth/releases
Author-email: Matin Tamizi <mtamizi@duck.com>
License: MIT
License-File: LICENSE
Keywords: garmin,garmin api,garmin connect,garmin sso
Classifier: Development Status :: 5 - Production/Stable
Classifier: License :: OSI Approved :: MIT License
Classifier: Operating System :: MacOS :: MacOS X
Classifier: Operating System :: Microsoft :: Windows
Classifier: Operating System :: OS Independent
Classifier: Operating System :: POSIX :: Linux
Classifier: Programming Language :: Python :: 3.10
Classifier: Programming Language :: Python :: 3.11
Classifier: Programming Language :: Python :: 3.12
Classifier: Programming Language :: Python :: 3.13
Classifier: Programming Language :: Python :: 3.14
Requires-Python: >=3.10
Requires-Dist: logfire<5.0,>=2.11
Requires-Dist: pydantic<3.0.0,>=1.10.12
Requires-Dist: requests-oauthlib<3.0.0,>=1.3.1
Requires-Dist: requests<3.0.0,>=2.0.0
Provides-Extra: docs
Requires-Dist: mkdocs-material>=9.5; extra == 'docs'
Requires-Dist: mkdocs>=1.6; extra == 'docs'
